Metadata-Version: 1.0
Name: EzAuth
Version: 0.0.2
Summary: Epic Games Python Authenticator with access to multiple authorization methods
Home-page: https://github.com/Jawschamp/EzAuth
Author: Jawschamp
Author-email: UNKNOWN
License: MIT
Platform: UNKNOWN
